ojitos369_postgres_db/__init__.py
ojitos369_postgres_db/postgres_db.py
ojitos369_postgres_db-2.1.4.dist-info/licenses/LICENSE.txt
ojitos369_postgres_db-2.1.4.dist-info/METADATA
ojitos369_postgres_db-2.1.4.dist-info/WHEEL
ojitos369_postgres_db-2.1.4.dist-info/top_level.txt
ojitos369_postgres_db-2.1.4.dist-info/RECORD
